README.md
setup.py
bin/c
commune/__init__.py
commune/sandbox.py
commune/module/__init__.py
commune/module/module.py
commune/module/peers.py
commune/module/tree.py
commune/module/config/__init__.py
commune/module/config/config.py
commune/module/config/utils.py
commune/modules/__init__.py
commune/modules/api.py
commune/modules/namespace.py
commune/modules/websocket.py
commune/modules/archive/__init__.py
commune/modules/archive/aggregator/__init__.py
commune/modules/archive/aggregator/base.py
commune/modules/archive/aggregator/mean.py
commune/modules/archive/aggregator/sum.py
commune/modules/archive/logger/__init__.py
commune/modules/archive/logger/logger_module.py
commune/modules/archive/pipeline/__init__.py
commune/modules/archive/pipeline/pipeline.py
commune/modules/archive/ray/__init__.py
commune/modules/archive/ray/actor_pool.py
commune/modules/archive/ray/queue.py
commune/modules/archive/ray/utils.py
commune/modules/archive/streamlit/__init__.py
commune/modules/archive/streamlit/streamlit_module.py
commune/modules/archive/streamlit/utils.py
commune/modules/archive/trl/__init__.py
commune/modules/archive/trl/core.py
commune/modules/archive/trl/import_utils.py
commune/modules/archive/trl/models/__init__.py
commune/modules/archive/trl/models/modeling_base.py
commune/modules/archive/trl/models/modeling_value_head.py
commune/modules/archive/trl/trainer/__init__.py
commune/modules/archive/trl/trainer/base.py
commune/modules/archive/trl/trainer/ppo_config.py
commune/modules/archive/trl/trainer/ppo_trainer.py
commune/modules/archive/trl/trainer/utils.py
commune/modules/cli/__init__.py
commune/modules/cli/__main__.py
commune/modules/cli/cli.py
commune/modules/client/__init__.py
commune/modules/client/client.py
commune/modules/client/ray/__init__.py
commune/modules/client/ray/ray.py
commune/modules/client/ray/utils.py
commune/modules/client/rest/__init__.py
commune/modules/client/rest/rest.py
commune/modules/client/rest/utils.py
commune/modules/client/s3/__init__.py
communeai.egg-info/PKG-INFO
communeai.egg-info/SOURCES.txt
communeai.egg-info/dependency_links.txt
communeai.egg-info/top_level.txt