Metadata-Version: 2.1
Name: communeai
Version: 0.0.1
Summary: commune-ai
Home-page: https://github.com/commune-ai/commune
Author: commune
Author-email: 
License: MIT
Project-URL: Bug Reports, https://github.com/commune-ai/commune/issues
Project-URL: Source, https://github.com/commune-ai/commune
Platform: UNKNOWN
Classifier: Development Status :: 3 - Alpha
Classifier: Intended Audience :: Developers
Classifier: Topic :: Software Development :: Build Tools
Classifier: Programming Language :: Python :: 3.11
Classifier: Programming Language :: Python :: 3.10
Classifier: Programming Language :: Python :: 3.9
Classifier: Programming Language :: Python :: 3.8
Requires-Python: >=3.8
